LetterCount/LetterCount.py
LetterCount/__init__.py
LetterCount-1.0.1.dist-info/LICENSE
LetterCount-1.0.1.dist-info/METADATA
LetterCount-1.0.1.dist-info/WHEEL
LetterCount-1.0.1.dist-info/top_level.txt
LetterCount-1.0.1.dist-info/RECORD
